bamboopy/__init__.py
bamboopy/bamboohr.py
bamboopy/base.py
bamboopy/error.py
bamboopy/logging_helper.py
bamboopy/resources.py
bamboopy-0.0.7.dist-info/LICENSE
bamboopy-0.0.7.dist-info/METADATA
bamboopy-0.0.7.dist-info/WHEEL
bamboopy-0.0.7.dist-info/top_level.txt
bamboopy-0.0.7.dist-info/RECORD
