Metadata-Version: 2.1
Name: bamboopy
Version: 0.0.7
Summary: A python wrapper around BambooHR's APIs
Home-page: https://github.com/gortiz-v/bamboopy
Author: Gerardo Ortiz
Author-email: gortiz@netquest.com
License: MIT
Keywords: Bamboo,HR,BambooHR,API
Platform: OS Independent
Classifier: Development Status :: 3 - Alpha
Classifier: License :: OSI Approved :: MIT License
Classifier: Operating System :: OS Independent
Classifier: Programming Language :: Python :: 3.6
Classifier: Intended Audience :: Developers
Classifier: Topic :: Software Development :: Libraries :: Python Modules
Requires-Dist: rfc6266
Requires-Dist: xmltodict
